pyUSID/__init__.py
pyUSID/__version__.py
pyUSID/io/__init__.py
pyUSID/io/anc_build_utils.py
pyUSID/io/array_translator.py
pyUSID/io/dimension.py
pyUSID/io/image.py
pyUSID/io/reg_ref.py
pyUSID/io/usi_data.py
pyUSID/io/hdf_utils/__init__.py
pyUSID/io/hdf_utils/base.py
pyUSID/io/hdf_utils/model.py
pyUSID/io/hdf_utils/simple.py
pyUSID/processing/__init__.py
pyUSID/processing/comp_utils.py
pyUSID/processing/process.py
pyUSID-0.0.12.dist-info/LICENSE
pyUSID-0.0.12.dist-info/METADATA
pyUSID-0.0.12.dist-info/WHEEL
pyUSID-0.0.12.dist-info/top_level.txt
pyUSID-0.0.12.dist-info/RECORD
