Metadata-Version: 2.1
Name: pyUSID
Version: 0.0.12
Summary: Framework for storing, visualizing, and processing Universal Spectroscopic and Imaging Data (USID)
Home-page: https://pycroscopy.github.io/pyUSID/about.html
Author: S. Somnath, C. R. Smith, and contributors
Author-email: pycroscopy@gmail.com
License: MIT
Keywords: imaging,spectra,multidimensional,data format,universal,hdf5
Platform: Linux
Platform: Mac OSX
Platform: Windows 10/8.1/8/7
Classifier: Development Status :: 4 - Beta
Classifier: Environment :: Console
Classifier: Intended Audience :: Science/Research
Classifier: License :: OSI Approved :: MIT License
Classifier: Natural Language :: English
Classifier: Operating System :: OS Independent
Classifier: Programming Language :: Cython
Classifier: Programming Language :: Python :: 3.7
Classifier: Programming Language :: Python :: 3.8
Classifier: Programming Language :: Python :: 3.9
Classifier: Programming Language :: Python :: Implementation :: CPython
Classifier: Topic :: Scientific/Engineering :: Information Analysis
License-File: LICENSE
Requires-Dist: numpy >=1.20
Requires-Dist: toolz
Requires-Dist: cytoolz
Requires-Dist: dask >=0.10
Requires-Dist: h5py >=2.6.0
Requires-Dist: pillow
Requires-Dist: psutil
Requires-Dist: six
Requires-Dist: sidpy >=0.10
Provides-Extra: mpi
Requires-Dist: mpi4py ; extra == 'mpi'
